MANIFEST.in
setup.cfg
setup.py
doc/dev.rst
doc/index.rst
doc/sqla_helpers.rst
sqla_helpers/__init__.py
sqla_helpers/base_model.py
sqla_helpers/loading.py
sqla_helpers/logical.py
sqla_helpers/process.py
sqla_helpers/utils.py
sqla_helpers.egg-info/PKG-INFO
sqla_helpers.egg-info/SOURCES.txt
sqla_helpers.egg-info/dependency_links.txt
sqla_helpers.egg-info/top_level.txt
sqla_helpers/tests/__init__.py
sqla_helpers/tests/class_test.py
sqla_helpers/tests/test_base_model.py
sqla_helpers/tests/test_process_params.py
sqla_helpers/tests/test_utils.py
sqla_helpers/tests/test_integration/__init__.py
sqla_helpers/tests/test_integration/test_count.py
sqla_helpers/tests/test_integration/test_filter.py
sqla_helpers/tests/test_integration/test_load.py