Metadata-Version: 1.1
Name: sqla-helpers
Version: 0.5.1
Summary: Provide some methods for getting objects with SQLAlchemy
Home-page: https://github.com/moumoutte/sqla_helpers/
Author: Guillaume Camera
Author-email: camera.g@gmail.com
License: UNKNOWN
Platform: UNKNOWN
Classifier: Programming Language :: Python
Classifier: License :: OSI Approved :: BSD License
Classifier: Natural Language :: French
Classifier: Operating System :: OS Independent
Classifier: Programming Language :: Python :: 2.7
Classifier: Topic :: Software Development :: Libraries :: Python Modules
Requires: nose
Requires: coverage
Requires: mock
Requires: sqlalchemy
